{
  "id": 11066,
  "language": "english",
  "hallucination": "no",
  "ground_truth_source": "text",
  "dialogue_data": {
    "dialogue_metadata": {
      "inferred_relationship": "Podcast co-hosts",
      "inferred_vibe": "Somber and informative"
    },
    "dialogue_turns": [
      {
        "speaker": "Host_A",
        "text": "Kicking off today's episode with some really somber news, unfortunately.",
        "tts_text": "Kicking off today's episode with some really somber news, unfortunately.",
        "check_worthy": false,
        "factual_label": "NEI",
        "evidence_snippet": ""
      },
      {
        "speaker": "Host_B",
        "text": "Yeah, it's pretty, uh, hard to hear about. What's the latest?",
        "tts_text": "Yeah, it's pretty, uh, hard to hear about. What's the latest?",
        "check_worthy": false,
        "factual_label": "NEI",
        "evidence_snippet": ""
      },
      {
        "speaker": "Host_A",
        "text": "So, there was this tragic incident, just on the evening of June 23rd, on the Otar Almaty-1 railway section.",
        "tts_text": "So, there was this tragic incident, just on the evening of June twenty third, on the Otar Almaty-one railway section.",
        "check_worthy": true,
        "factual_label": "True",
        "evidence_snippet": "A tragic incident occurred on the evening of June 23 on the Otar \" Almaty-1 section of the railway.",
        "confidence": 1.0,
        "priority": "high"
      },
      {
        "speaker": "Host_B",
        "text": "Oh, like, the train tracks?",
        "tts_text": "Oh, like, the train tracks?",
        "check_worthy": false,
        "factual_label": "NEI",
        "evidence_snippet": ""
      },
      {
        "speaker": "Host_A",
        "text": "Exactly. Two people, um, entered the tracks at an unauthorized spot and were struck by a train.",
        "tts_text": "Exactly. Two people, um, entered the tracks at an unauthorized spot and were struck by a train.",
        "check_worthy": true,
        "factual_label": "True",
        "evidence_snippet": "Two individuals entered the tracks and were struck by a train. ... Two people suddenly stepped onto the tracks at an unauthorized location...",
        "confidence": 1.0,
        "priority": "high"
      },
      {
        "speaker": "Host_B",
        "text": "Oh, no. That's just... [overlaps]",
        "tts_text": "Oh, no. That's just...",
        "check_worthy": false,
        "factual_label": "NEI",
        "evidence_snippet": ""
      },
      {
        "speaker": "Host_A",
        "text": "[interrupts] Yeah, it's awful. The Kazakhstan Temir Zholy press service shared the details.",
        "tts_text": "Yeah, it's awful. The Kazakhstan Temir Zholy press service shared the details.",
        "check_worthy": true,
        "factual_label": "True",
        "evidence_snippet": "Details of the incident were shared by the \"Kazakhstan Temir Zholy\" press service.",
        "confidence": 1.0,
        "priority": "high"
      },
      {
        "speaker": "Host_B",
        "text": "So, like, they just walked onto the tracks?",
        "tts_text": "So, like, they just walked onto the tracks?",
        "check_worthy": false,
        "factual_label": "NEI",
        "evidence_snippet": ""
      },
      {
        "speaker": "Host_A",
        "text": "Apparently. Between Aksenger and Burunday. They just stepped out in front of an oncoming train, trying to cross.",
        "tts_text": "Apparently. Between Aksenger and Burunday. They just stepped out in front of an oncoming train, trying to cross.",
        "check_worthy": true,
        "factual_label": "True",
        "evidence_snippet": "According to the press service, the incident took place between Aksenger and Burunday. Two people suddenly stepped onto the tracks at an unauthorized location in front of an oncoming train and attempted to cross to the other side.",
        "confidence": 1.0,
        "priority": "high"
      },
      {
        "speaker": "Host_B",
        "text": "And the driver, um, couldn't stop?",
        "tts_text": "And the driver, um, couldn't stop?",
        "check_worthy": false,
        "factual_label": "NEI",
        "evidence_snippet": ""
      },
      {
        "speaker": "Host_A",
        "text": "Right. They sounded the horn, but the individuals didn't respond. And with such a short distance, the train just couldn't stop in time.",
        "tts_text": "Right. They sounded the horn, but the individuals didn't respond. And with such a short distance, the train just couldn't stop in time.",
        "check_worthy": true,
        "factual_label": "True",
        "evidence_snippet": "The train driver sounded the horn, but the individuals did not respond. Due to the short distance, the train was unable to stop in time.",
        "confidence": 1.0,
        "priority": "high"
      },
      {
        "speaker": "Host_B",
        "text": "Wow. So, both pedestrians... [trails off sadly]",
        "tts_text": "Wow. So, both pedestrians...",
        "check_worthy": false,
        "factual_label": "NEI",
        "evidence_snippet": ""
      },
      {
        "speaker": "Host_A",
        "text": "Yeah, both died as a result. And now, the Transport Police, they've launched a criminal investigation into, like, railway safety violations.",
        "tts_text": "Yeah, both died as a result. And now, the Transport Police, they've launched a criminal investigation into, like, railway safety violations.",
        "check_worthy": true,
        "factual_label": "True",
        "evidence_snippet": "Both pedestrians died as a result. The Transport Police Department has launched a criminal investigation into the violation of railway safety rules that led to the accidental death of two or more people.",
        "confidence": 1.0,
        "priority": "high"
      },
      {
        "speaker": "Host_B",
        "text": "Which, you know, makes sense. I mean, it's incredibly dangerous to be on the tracks.",
        "tts_text": "Which, you know, makes sense. I mean, it's incredibly dangerous to be on the tracks.",
        "check_worthy": false,
        "factual_label": "NEI",
        "evidence_snippet": ""
      },
      {
        "speaker": "Host_A",
        "text": "Absolutely. And it's not even the first close call recently, remember that bus in Zhambyl region?",
        "tts_text": "Absolutely. And it's not even the first close call recently, remember that bus in Zhambyl region?",
        "check_worthy": true,
        "factual_label": "True",
        "evidence_snippet": "Previously, a passenger train narrowly avoided a collision with a bus that drove onto the tracks in the Zhambyl region.",
        "confidence": 1.0,
        "priority": "high"
      },
      {
        "speaker": "Host_B",
        "text": "Oh, yeah! The one that almost got hit by a passenger train. Jeez.",
        "tts_text": "Oh, yeah! The one that almost got hit by a passenger train. Jeez.",
        "check_worthy": true,
        "factual_label": "True",
        "evidence_snippet": "Previously, a passenger train narrowly avoided a collision with a bus that drove onto the tracks in the Zhambyl region.",
        "confidence": 1.0,
        "priority": "high"
      },
      {
        "speaker": "Host_A",
        "text": "So, just a stark reminder, uh, of railway safety, or the lack thereof, sometimes.",
        "tts_text": "So, just a stark reminder, uh, of railway safety, or the lack thereof, sometimes.",
        "check_worthy": false,
        "factual_label": "NEI",
        "evidence_snippet": ""
      },
      {
        "speaker": "Host_B",
        "text": "Definitely. Really, really tragic.",
        "tts_text": "Definitely. Really, really tragic.",
        "check_worthy": false,
        "factual_label": "NEI",
        "evidence_snippet": ""
      }
    ]
  }
}